fakecouch.py
fakecouch-0.0.15.dist-info/METADATA
fakecouch-0.0.15.dist-info/RECORD
fakecouch-0.0.15.dist-info/WHEEL
fakecouch-0.0.15.dist-info/top_level.txt
