Metadata-Version: 2.1
Name: fakecouch
Version: 0.0.15
Summary: Fake implementation of CouchDBKit api for testing purposes
Home-page: http://github.com/dimagi/fakecouch
Author: Dimagi
Author-email: dev@dimagi.com
License: MIT
Platform: UNKNOWN
